qth/__init__.py
qth/version.py
qth-0.7.1.dist-info/METADATA
qth-0.7.1.dist-info/WHEEL
qth-0.7.1.dist-info/top_level.txt
qth-0.7.1.dist-info/RECORD
