Metadata-Version: 2.1
Name: qth
Version: 0.7.1
Summary: Qb-Than's Home-automation messaging library.
Home-page: https://github.com/mossblaser/qth
Author: Jonathan Heathcote
License: GPLv2
Keywords: mqtt asyncio home-automation messaging
Classifier: Development Status :: 3 - Alpha
Classifier: Intended Audience :: Developers
Classifier: License :: OSI Approved :: GNU General Public License v2 (GPLv2)
Classifier: Operating System :: POSIX :: Linux
Classifier: Operating System :: Microsoft :: Windows
Classifier: Operating System :: MacOS
Classifier: Programming Language :: Python :: 3
Classifier: Programming Language :: Python :: 3.10
Requires-Dist: aiomqtt <1.0.0,>=0.1.0
Requires-Dist: sentinel >=0.1.1
